crim_intervals/__init__.py
crim_intervals/corpus_tools.py
crim_intervals/data/cadences/CVFLabels.csv
crim_intervals/data/cadences/cadenceLabels.csv
crim_intervals/data/cadences/groundTruth.csv
crim_intervals/main.py
crim_intervals/main_objs.py
crim_intervals/networks.py
crim_intervals/sorting_lists.py
crim_intervals/test_cadences.py
crim_intervals/test_constants.py
crim_intervals/test_main_objs.py
crim_intervals/test_vis.py
crim_intervals/visualizations.py
crim_intervals-2.0.62.dist-info/METADATA
crim_intervals-2.0.62.dist-info/WHEEL
crim_intervals-2.0.62.dist-info/RECORD
