Metadata-Version: 2.4
Name: crim_intervals
Version: 2.0.62
Summary: CRIM intervals package
License: creative commons
Author: Richard Freedman
Author-email: rfreedma@haverford.edu
Requires-Python: >=3.9
Classifier: License :: Other/Proprietary License
Classifier: Programming Language :: Python :: 3
Classifier: Programming Language :: Python :: 3.9
Classifier: Programming Language :: Python :: 3.10
Classifier: Programming Language :: Python :: 3.11
Classifier: Programming Language :: Python :: 3.12
Classifier: Programming Language :: Python :: 3.13
Classifier: Programming Language :: Python :: 3.14
Requires-Dist: altair (==5.2.0)
Requires-Dist: certifi (==2020.12.5)
Requires-Dist: chardet (==4.0.0)
Requires-Dist: h11 (==0.14.0)
Requires-Dist: httpcore (==1.0.2)
Requires-Dist: httpx (==0.27.0)
Requires-Dist: idna (==3.1)
Requires-Dist: ipython (>=7.23.1,<8.0)
Requires-Dist: joblib (>=1.5.2,<2.0.0)
Requires-Dist: jsonschema (>=3.1)
Requires-Dist: lxml (==5.1.0)
Requires-Dist: matplotlib (>=3.9.2,<4.0.0)
Requires-Dist: more-itertools (==8.7.0)
Requires-Dist: music21 (==8.3.0)
Requires-Dist: numpy (>=1.20.2,<2.0.0)
Requires-Dist: pandas (>=2.2.0)
Requires-Dist: plotly (==5.19.0)
Requires-Dist: plotly-express (==0.4.1)
Requires-Dist: pyarrow (>=15.0.0)
Requires-Dist: python-dateutil (==2.8.2)
Requires-Dist: python-louvain (==0.16)
Requires-Dist: pytz (==2021.1)
Requires-Dist: pyvis (==0.1.9)
Requires-Dist: requests (==2.31.0)
Requires-Dist: rfc3986 (==1.4.0)
Requires-Dist: seaborn (==0.13)
Requires-Dist: six (==1.16.0)
Requires-Dist: sniffio (==1.2.0)
Requires-Dist: statsmodels (==0.14.1)
Requires-Dist: textdistance (==4.2.1)
Requires-Dist: verovio (==5.5.0)
Requires-Dist: webcolors (==1.11.1)
Requires-Dist: xlsxwriter (==3.0.2)
